[
  { "employee_id": "n063", "first_name": "Friedrick", "last_name": "Petracco" },
  { "employee_id": "d160", "first_name": "Jamison", "last_name": "Vicarey" },
  { "employee_id": "l858", "first_name": "Janessa", "last_name": "Elliott" },
  { "employee_id": "n036", "first_name": "Maryjo", "last_name": "Yaneev" },
  { "employee_id": "h119", "first_name": "Filbert", "last_name": "Karran" },
  { "employee_id": "j058", "first_name": "Anett", "last_name": "Roney" },
  { "employee_id": "p251", "first_name": "Curcio", "last_name": "Goldsberry" },
  { "employee_id": "k206", "first_name": "Mendy", "last_name": "Effemy" },
  { "employee_id": "a371", "first_name": "Ariela", "last_name": "Gates" },
  { "employee_id": "l446", "first_name": "Colby", "last_name": "Johannes" },
  { "employee_id": "v428", "first_name": "Loy", "last_name": "Coye" },
  { "employee_id": "w559", "first_name": "Paco", "last_name": "Sinton" },
  { "employee_id": "n160", "first_name": "Alisun", "last_name": "Guesford" },
  { "employee_id": "v183", "first_name": "Paton", "last_name": "Lyenyng" },
  { "employee_id": "l534", "first_name": "Jodie", "last_name": "Capstick" },
  { "employee_id": "i762", "first_name": "Pip", "last_name": "Tuckie" },
  { "employee_id": "f581", "first_name": "Eugine", "last_name": "Carvill" },
  { "employee_id": "b552", "first_name": "Ezechiel", "last_name": "Cargo" },
  {
    "employee_id": "c096",
    "first_name": "Henderson",
    "last_name": "Wedderburn"
  },
  { "employee_id": "j247", "first_name": "Cristen", "last_name": "Patzelt" }
]
